nuclearmasses/__init__.py
nuclearmasses/ame_mass_file.py
nuclearmasses/ame_mass_parse.py
nuclearmasses/ame_reaction_1_file.py
nuclearmasses/ame_reaction_1_parse.py
nuclearmasses/ame_reaction_2_file.py
nuclearmasses/ame_reaction_2_parse.py
nuclearmasses/mass_table.py
nuclearmasses/nubase_file.py
nuclearmasses/nubase_parse.py
nuclearmasses/parse.py
nuclearmasses/data/2003/mass.mas03
nuclearmasses/data/2003/nubtab03.asc
nuclearmasses/data/2003/rct1.mas03
nuclearmasses/data/2003/rct2.mas03
nuclearmasses/data/2012/mass.mas12
nuclearmasses/data/2012/nubtab12.asc
nuclearmasses/data/2012/rct1.mas12
nuclearmasses/data/2012/rct2.mas12
nuclearmasses/data/2016/mass16.txt
nuclearmasses/data/2016/nubase2016.txt
nuclearmasses/data/2016/rct1-16.txt
nuclearmasses/data/2016/rct2-16.txt
nuclearmasses/data/2020/mass.mas20
nuclearmasses/data/2020/nubase_1.mas20
nuclearmasses/data/2020/rct1.mas20
nuclearmasses/data/2020/rct2.mas20
nuclearmasses-0.0.1.dist-info/licenses/LICENSE
nuclearmasses-0.0.1.dist-info/METADATA
nuclearmasses-0.0.1.dist-info/WHEEL
nuclearmasses-0.0.1.dist-info/top_level.txt
nuclearmasses-0.0.1.dist-info/RECORD
